[
    {
      "id": 1,
      "facilities_id": "Lt01",
      "title": "Laptop",
      "price": "1.500.000đ",
      "qty": 10,
      "image": "https://cdn.tgdd.vn/Files/2019/08/22/1190454/laptop-vien-man-hinh-mong-co-nhung-uu-va-nhuoc-diem-gi--4.jpg",
      "innitiated_date": "12/01/2020",
      "emp_ID": "NV02",
      "fullName": "Trần Hữu Lương"
    },
    {
      "id": 2,
      "facilities_id": "Mi01",
      "title": "Máy In",
      "price": "700.000đ",
      "qty": 20,
      "image": "https://smartid.vn/templates/pictures/content/SmartID-may-in-anh-ky-thuat-so-600px(1).jpg",
      "innitiated_date": "12/05/2020",
      "emp_ID": "NV04",
      "fullName": "Dương Thị Thùy Dung"
    },
    {
      "id": 3,
      "facilities_id": "Pc01",
      "title": "Máy Tính Để Bàn",
      "price": "12.500.000đ",
      "qty": 20,
      "image": "https://khadao.vn/uploads/tiny_uploads/tin%20tuc/5%20C%E1%BA%A4U%20H%C3%8CNH%20PC/build-pc-gaming-duoi-1o-tr.jpg",
      "innitiated_date": "12/03/2020",
      "emp_ID": "NV04",
      "fullName": "Dương Thị Thùy Dung"
    },
    {
      "id": 4,
      "facilities_id": "Mcp20",
      "title": "Máy chiếu panasonic",
      "price": "9.500.000đ",
      "qty": 20,
      "image": "https://itbuy.vn/media/product/1271_pt_vx430_1.jpg",
      "innitiated_date": "20/01/2020",
      "emp_ID": "NV05",
      "fullName": "Võ Trung Hiếu"
    },
    {
      "id": 5,
      "facilities_id": "Mq220",
      "title": "Máy Quạt",
      "price": "5.000.000đ",
      "qty": 50,
      "image": "https://dienmayhangphu01.files.wordpress.com/2016/01/quat-treo-cong-nghiep-david-ydw-500-tw.jpg?w=640",
      "innitiated_date": "12/01/2021",
      "emp_ID": "NV02",
      "fullName": "Trần Hữu Lương"
    },
    {
      "id": 6,
      "facilities_id": "Mcb110",
      "title": "Máy Chiếu BeenQ",
      "price": "6.000.000đ",
      "qty": 50,
      "image": "https://meta.vn/Data/image/2020/06/11/may-chieu-ben-q-ms-506-1.jpg",
      "innitiated_date": "12/12/2021",
      "emp_ID": "NV02",
      "fullName": "Trần Hữu Lương"
    },
    {
      "id": 7,
      "facilities_id": "Mcb110",
      "title": "Máy Chiếu Mini EPSON",
      "price": "1.900.000đ",
      "qty": 50,
      "image": "https://saomaisg.vn/uploads/products/5b18f03b16df8.jpg",
      "innitiated_date": "21/08/2020",
      "emp_ID": "NV02",
      "fullName": "Trần Hữu Lương"
    },
    {
      "id": 8,
      "facilities_id": "Mcxm110",
      "title": "Máy Chiếu Xiaomi",
      "price": "10.500.000đ",
      "qty": 50,
      "image": "http://img.websosanh.vn/v2/users/root_product/images/may-chieu-laser-xiaomi/mdpwyqxgyrkvs.jpg",
      "innitiated_date": "20/01/2020",
      "emp_ID": "NV05",
      "fullName": "Võ Trung Hiếu"
    },
    {
      "id": 9,
      "facilities_id": "Table09",
      "title": "Bàn Gỗ",
      "price": "2.000.000đ",
      "qty": 50,
      "image": "https://bizweb.dktcdn.net/thumb/grande/100/245/838/products/64-p-1358910350911.jpg?v=1503051646970",
      "innitiated_date": "30/08/2020",
      "emp_ID": "NV05",
      "fullName": "Võ Trung Hiếu"
    },
    {
      "id": 10,
      "facilities_id": "Chair10",
      "title": "Ghế",
      "price": "700.000đ",
      "qty": 50,
      "image": "https://banghehatram.com/wp-content/uploads/2017/04/gh%E1%BA%BF-c08c-cover.jpg",
      "innitiated_date": "22/9/2020",
      "emp_ID": "NV05",
      "fullName": "Võ Trung Hiếu"
    },
    {
      "facilities_id": "Clothing11",
      "title": "Áo Đồng Phục",
      "price": "700.000đ",
      "qty": "100",
      "image": "https://maydongphucglu.com/wp-content/uploads/2018/03/AO-THUN-MIGROUP.jpg",
      "innitiated_date": "30/1/2022",
      "emp_ID": "NV05",
      "fullName": "Võ Trung Hiếu",
      "id": 11
    },
    {
      "facilities_id": "Camera12",
      "title": "Camera An Ninh",
      "price": "3.000.000đ",
      "qty": "20",
      "image": "https://channel.mediacdn.vn/2020/8/19/photo-1-1597823118182621480091.jpg",
      "innitiated_date": "30/1/2022",
      "emp_ID": "NV28",
      "fullName": "Dương Thu Giang",
      "id": 12
    },
    {
      "facilities_id": "Phone22",
      "title": "Điện Thoại Di Động",
      "price": "15000000",
      "qty": "100",
      "image": "https://storage.googleapis.com/cdn.nhanh.vn/store2/81120/ps/20211024/xsm.jpg",
      "innitiated_date": "27/01/2022",
      "emp_ID": "NV02",
      "fullName": "Trần Hữu Lương",
      "id": 14
    },
    {
      "facilities_id": "Girl14",
      "title": "Nữ Sinh",
      "price": "40000000",
      "qty": "10",
      "image": "https://pdp.edu.vn/wp-content/uploads/2021/06/hinh-anh-gai-xinh-de-thuong-nhat-1.jpg",
      "innitiated_date": "27/01/2022",
      "emp_ID": "NV03",
      "fullName": "Nguyễn Sỹ Dũng",
      "id": 15
    },
    {
      "facilities_id": "TV15",
      "title": "Tivi Thông Minh",
      "price": "25.000.000đ",
      "qty": "145",
      "image": "https://image-us.24h.com.vn/upload/4-2021/images/2021-12-29/dau-la-chiec-Smart-TV-xin-so-nhat-the-gioi-samsung-qled-1640754003-841-width660height366.jpg",
      "innitiated_date": "2022-01-14",
      "emp_ID": "NV03",
      "fullName": "Nguyễn Sỹ Dũng",
      "id": 16
    }
  ]